coinsta/__init__.py
coinsta/core.py
coinsta/exceptions.py
coinsta/utils.py
coinsta-0.1.8.dist-info/LICENSE
coinsta-0.1.8.dist-info/METADATA
coinsta-0.1.8.dist-info/WHEEL
coinsta-0.1.8.dist-info/top_level.txt
coinsta-0.1.8.dist-info/zip-safe
coinsta-0.1.8.dist-info/RECORD
