Metadata-Version: 2.1
Name: coinsta
Version: 0.1.8
Summary: A Python package for acquiring both historical and current data of cryptocurrencies.
Home-page: https://github.com/PyDataBlog/Coinsta
Author: Bernard Brenyah
Author-email: bbrenyah@gmail.com
License: BSD 3-Clause License
Platform: UNKNOWN
Classifier: Development Status :: 4 - Beta
Classifier: Programming Language :: Python
Classifier: Programming Language :: Python :: 3 :: Only
Classifier: Programming Language :: Python :: 3.6
Classifier: Programming Language :: Python :: 3.7
Classifier: Programming Language :: Python :: 3.8
Classifier: License :: OSI Approved :: BSD License
Requires-Dist: requests (==2.23.0)
Requires-Dist: pandas (==1.0.3)
Requires-Dist: lxml (==4.5.0)
Requires-Dist: html5lib (==1.0.1)
Requires-Dist: beautifulsoup4 (==4.9.0)
